aio_pika_msgpack_rpc/__init__.py
aio_pika_msgpack_rpc/msgpack_rpc.py
aio_pika_msgpack_rpc-1.0.2.dist-info/LICENSE
aio_pika_msgpack_rpc-1.0.2.dist-info/METADATA
aio_pika_msgpack_rpc-1.0.2.dist-info/WHEEL
aio_pika_msgpack_rpc-1.0.2.dist-info/top_level.txt
aio_pika_msgpack_rpc-1.0.2.dist-info/RECORD
