Metadata-Version: 2.1
Name: aio-pika-msgpack-rpc
Version: 1.0.2
Summary: aio-pika-msgpack-rpc
Author-email: DrFormatC <formacevt@bk.ru>
Project-URL: Homepage, https://github.com/DrFormat/aio-pika-msgpack-rpc
Project-URL: Bug Tracker, https://github.com/DrFormat/aio-pika-msgpack-rpc/issues
Classifier: Programming Language :: Python :: 3
Classifier: Programming Language :: Python :: 3.7
Classifier: Programming Language :: Python :: 3.8
Classifier: Programming Language :: Python :: 3.9
Classifier: Programming Language :: Python :: 3.10
Classifier: License :: OSI Approved :: MIT License
Classifier: Operating System :: OS Independent
Requires-Python: >=3.7
License-File: LICENSE
Requires-Dist: aio-pika (>=8.2.4)
Requires-Dist: msgpack (>=1.0.2)
